covid19DashCode/__init__.py
covid19DashCode/application.py
covid19DashCode/covid_data_handler.py
covid19DashCode/covid_news_handling.py
Cov19DashJacobBeeson-0.0.1.dist-info/LICENSE.txt
Cov19DashJacobBeeson-0.0.1.dist-info/METADATA
Cov19DashJacobBeeson-0.0.1.dist-info/WHEEL
Cov19DashJacobBeeson-0.0.1.dist-info/top_level.txt
Cov19DashJacobBeeson-0.0.1.dist-info/RECORD
