Metadata-Version: 2.1
Name: Cov19DashJacobBeeson
Version: 0.0.1
Summary: A a simple personalised covid information dashboard.
Home-page: https://github.com/JacobBeeson/Cov19Dashboard.git
Author: Jacob Beeson
Author-email: jtb215@exeter.ac.uk
License: UNKNOWN
Platform: UNKNOWN
Classifier: Programming Language :: Python :: 3
Classifier: License :: OSI Approved :: MIT License
Classifier: Operating System :: OS Independent
Requires-Python: >=3.9
License-File: LICENSE.txt
